{"photo":{"id":"2661602751","secret":"7bd76f533e","server":"3023","farm":4,"dateuploaded":"1215900338","isfavorite":0,"license":"4","safety_level":"0","rotation":0,"originalsecret":"fa129a3b39","originalformat":"jpg","owner":{"nsid":"7282451@N02","username":"Field Outdoor Spaces","realname":"","location":"","iconserver":"7405","iconfarm":8,"path_alias":null},"title":{"_content":"Rockwork planting"},"description":{"_content":""},"visibility":{"ispublic":1,"isfriend":0,"isfamily":0},"dates":{"posted":"1215900338","taken":"2008-07-12 15:05:38","takengranularity":"0","takenunknown":0,"lastupdate":"1325620819"},"views":"1552","editability":{"cancomment":0,"canaddmeta":0},"publiceditability":{"cancomment":1,"canaddmeta":0},"usage":{"candownload":1,"canblog":0,"canprint":0,"canshare":1},"comments":{"_content":"0"},"notes":{"note":[]},"people":{"haspeople":0},"tags":{"tag":[{"id":"7262103-2661602751-612846","author":"7282451@N02","authorname":"Field Outdoor Spaces","raw":"rain garden","_content":"raingarden","machine_tag":0},{"id":"7262103-2661602751-528867","author":"7282451@N02","authorname":"Field Outdoor Spaces","raw":"plantings","_content":"plantings","machine_tag":0},{"id":"7262103-2661602751-1049776","author":"7282451@N02","authorname":"Field Outdoor Spaces","raw":"steppers","_content":"steppers","machine_tag":0},{"id":"7262103-2661602751-80312999","author":"7282451@N02","authorname":"Field Outdoor Spaces","raw":"wall traprock","_content":"walltraprock","machine_tag":0},{"id":"7262103-2661602751-25583","author":"7282451@N02","authorname":"Field Outdoor Spaces","raw":"loch","_content":"loch","machine_tag":0}]},"urls":{"url":[{"type":"photopage","_content":"https:\/\/www.flickr.com\/photos\/7282451@N02\/2661602751\/"}]},"media":"photo"},"stat":"ok"}