{"photo":{"id":"14407991452","secret":"380d13406b","server":"2899","farm":3,"dateuploaded":"1402621797","isfavorite":0,"license":"2","safety_level":"0","rotation":0,"originalsecret":"cb3e0606e5","originalformat":"jpg","owner":{"nsid":"32194387@N02","username":"smilla4","realname":"","location":"Maine coast, U.S.A.","iconserver":"5333","iconfarm":6,"path_alias":"smilla4"},"title":{"_content":"Petal Drift in Steady Rain"},"description":{"_content":"Maine"},"visibility":{"ispublic":1,"isfriend":0,"isfamily":0},"dates":{"posted":"1402621797","taken":"2014-06-04 07:38:11","takengranularity":"0","takenunknown":0,"lastupdate":"1427503807"},"views":"702","editability":{"cancomment":0,"canaddmeta":0},"publiceditability":{"cancomment":1,"canaddmeta":0},"usage":{"candownload":1,"canblog":0,"canprint":0,"canshare":1},"comments":{"_content":"8"},"notes":{"note":[]},"people":{"haspeople":0},"tags":{"tag":[{"id":"32174039-14407991452-1483","author":"32194387@N02","authorname":"smilla4","raw":"garden","_content":"garden","machine_tag":0},{"id":"32174039-14407991452-4862","author":"32194387@N02","authorname":"smilla4","raw":"terrace","_content":"terrace","machine_tag":0},{"id":"32174039-14407991452-931","author":"32194387@N02","authorname":"smilla4","raw":"rain","_content":"rain","machine_tag":0},{"id":"32174039-14407991452-758956","author":"32194387@N02","authorname":"smilla4","raw":"white petals","_content":"whitepetals","machine_tag":0},{"id":"32174039-14407991452-864088","author":"32194387@N02","authorname":"smilla4","raw":"fallen petals","_content":"fallenpetals","machine_tag":0},{"id":"32174039-14407991452-308","author":"32194387@N02","authorname":"smilla4","raw":"sculpture","_content":"sculpture","machine_tag":0},{"id":"32174039-14407991452-968","author":"32194387@N02","authorname":"smilla4","raw":"June","_content":"june","machine_tag":0},{"id":"32174039-14407991452-1389","author":"32194387@N02","authorname":"smilla4","raw":"fence","_content":"fence","machine_tag":0},{"id":"32174039-14407991452-556","author":"32194387@N02","authorname":"smilla4","raw":"tree","_content":"tree","machine_tag":0},{"id":"32174039-14407991452-586","author":"32194387@N02","authorname":"smilla4","raw":"green","_content":"green","machine_tag":0},{"id":"32174039-14407991452-7243","author":"32194387@N02","authorname":"smilla4","raw":"Maine","_content":"maine","machine_tag":0}]},"urls":{"url":[{"type":"photopage","_content":"https:\/\/www.flickr.com\/photos\/smilla4\/14407991452\/"}]},"media":"photo"},"stat":"ok"}