{"photo":{"id":"14366905365","secret":"61fd59ae38","server":"3911","farm":4,"dateuploaded":"1402155617","isfavorite":0,"license":"0","safety_level":"0","rotation":0,"owner":{"nsid":"69711280@N00","username":"Dagonite","realname":"","location":"USA","iconserver":"92","iconfarm":1,"path_alias":"dagonite"},"title":{"_content":"Dr. Sun Yat-Sen Classical Chinese Garden"},"description":{"_content":"Sony A7R with Zeiss 24-70 F\/2.8                               "},"visibility":{"ispublic":1,"isfriend":0,"isfamily":0},"dates":{"posted":"1402155617","taken":"2014-05-25 12:22:59","takengranularity":"0","takenunknown":0,"lastupdate":"1402155622"},"views":"279","editability":{"cancomment":0,"canaddmeta":0},"publiceditability":{"cancomment":1,"canaddmeta":0},"usage":{"candownload":0,"canblog":0,"canprint":0,"canshare":1},"comments":{"_content":"0"},"notes":{"note":[]},"people":{"haspeople":0},"tags":{"tag":[{"id":"4403885-14366905365-1218","author":"69711280@N00","authorname":"Dagonite","raw":"vancouver","_content":"vancouver","machine_tag":0},{"id":"4403885-14366905365-451","author":"69711280@N00","authorname":"Dagonite","raw":"Canada","_content":"canada","machine_tag":0},{"id":"4403885-14366905365-7156","author":"69711280@N00","authorname":"Dagonite","raw":"Chinese","_content":"chinese","machine_tag":0},{"id":"4403885-14366905365-1483","author":"69711280@N00","authorname":"Dagonite","raw":"Garden","_content":"garden","machine_tag":0},{"id":"4403885-14366905365-153242","author":"69711280@N00","authorname":"Dagonite","raw":"Dr. Sun Yat-Sen Classical Chinese Garden","_content":"drsunyatsenclassicalchinesegarden","machine_tag":0},{"id":"4403885-14366905365-145286494","author":"69711280@N00","authorname":"Dagonite","raw":"Sony A7R","_content":"sonya7r","machine_tag":0},{"id":"4403885-14366905365-41985023","author":"69711280@N00","authorname":"Dagonite","raw":"Zeiss 24-70mm F\/2.8","_content":"zeiss2470mmf28","machine_tag":0},{"id":"4403885-14366905365-3350","author":"69711280@N00","authorname":"Dagonite","raw":"China Town","_content":"chinatown","machine_tag":0},{"id":"4403885-14366905365-13580","author":"69711280@N00","authorname":"Dagonite","raw":"Rainy","_content":"rainy","machine_tag":0},{"id":"4403885-14366905365-931","author":"69711280@N00","authorname":"Dagonite","raw":"Rain","_content":"rain","machine_tag":0}]},"urls":{"url":[{"type":"photopage","_content":"https:\/\/www.flickr.com\/photos\/dagonite\/14366905365\/"}]},"media":"photo"},"stat":"ok"}