{"photo":{"id":"8537615930","secret":"acfd79da64","server":"8247","farm":9,"dateuploaded":"1362681200","isfavorite":0,"license":"0","safety_level":"0","rotation":0,"originalsecret":"24a169e8e6","originalformat":"jpg","owner":{"nsid":"91827182@N05","username":"Sweetlassie","realname":"Charmaine McInnis","location":"New Minas, Nova Scotia, Canada","iconserver":"5347","iconfarm":6,"path_alias":"sweetlassie"},"title":{"_content":"An English Country Garden, Broadway"},"description":{"_content":"Although its raining I couldn't resist to take a shot of this lovely English garden in Broadway."},"visibility":{"ispublic":1,"isfriend":0,"isfamily":0},"dates":{"posted":"1362681200","taken":"2006-05-01 00:00:00","takengranularity":"4","takenunknown":0,"lastupdate":"1421156313"},"views":"1246","editability":{"cancomment":0,"canaddmeta":0},"publiceditability":{"cancomment":1,"canaddmeta":0},"usage":{"candownload":1,"canblog":0,"canprint":0,"canshare":1},"comments":{"_content":"1"},"notes":{"note":[]},"people":{"haspeople":0},"tags":{"tag":[{"id":"91821842-8537615930-279","author":"91827182@N05","authorname":"Sweetlassie","raw":"england","_content":"england","machine_tag":0},{"id":"91821842-8537615930-9325","author":"91827182@N05","authorname":"Sweetlassie","raw":"cotswolds","_content":"cotswolds","machine_tag":0},{"id":"91821842-8537615930-7282","author":"91827182@N05","authorname":"Sweetlassie","raw":"broadway","_content":"broadway","machine_tag":0},{"id":"91821842-8537615930-1483","author":"91827182@N05","authorname":"Sweetlassie","raw":"garden","_content":"garden","machine_tag":0}]},"location":{"latitude":"52.040666","longitude":"-1.853942","accuracy":"11","context":"0","locality":{"_content":"Broadway","place_id":"u8c3CgpQVrqyIA","woeid":"14040"},"county":{"_content":"Worcestershire","place_id":"2dIS7FdQULzNwaAfKg","woeid":"12602192"},"region":{"_content":"England","place_id":"2eIY2QFTVr_DwWZNLg","woeid":"24554868"},"country":{"_content":"United Kingdom","place_id":"cnffEpdTUb5v258BBA","woeid":"23424975"},"place_id":"u8c3CgpQVrqyIA","woeid":"14040"},"geoperms":{"ispublic":1,"iscontact":0,"isfriend":0,"isfamily":0},"urls":{"url":[{"type":"photopage","_content":"https:\/\/www.flickr.com\/photos\/sweetlassie\/8537615930\/"}]},"media":"photo"},"stat":"ok"}