{"photo":{"id":"14090480679","secret":"fb253f6875","server":"5555","farm":6,"dateuploaded":"1401135144","isfavorite":0,"license":"0","safety_level":"0","rotation":0,"owner":{"nsid":"47434210@N08","username":"GeneInman.com","realname":"Gene Inman","location":"Houston, Texas, USA  \/  Hamburg, Germany, \/ Singapore ","iconserver":"7411","iconfarm":8,"path_alias":"gene_inman"},"title":{"_content":"City Garden, Rain"},"description":{"_content":"iPad image - mein garden"},"visibility":{"ispublic":1,"isfriend":0,"isfamily":0},"dates":{"posted":"1401135144","taken":"2014-05-26 15:05:10","takengranularity":"0","takenunknown":0,"lastupdate":"1429107042"},"views":"764","editability":{"cancomment":0,"canaddmeta":0},"publiceditability":{"cancomment":1,"canaddmeta":0},"usage":{"candownload":0,"canblog":0,"canprint":0,"canshare":1},"comments":{"_content":"0"},"notes":{"note":[]},"people":{"haspeople":0},"tags":{"tag":[{"id":"47341397-14090480679-1483","author":"47434210@N08","authorname":"GeneInman.com","raw":"Garden","_content":"garden","machine_tag":0},{"id":"47341397-14090480679-931","author":"47434210@N08","authorname":"GeneInman.com","raw":"rain","_content":"rain","machine_tag":0},{"id":"47341397-14090480679-394149","author":"47434210@N08","authorname":"GeneInman.com","raw":"iPad","_content":"ipad","machine_tag":0},{"id":"47341397-14090480679-57507617","author":"47434210@N08","authorname":"GeneInman.com","raw":"Gene Inman Photography","_content":"geneinmanphotography","machine_tag":0},{"id":"47341397-14090480679-57538345","author":"47434210@N08","authorname":"GeneInman.com","raw":"GeneInman.com","_content":"geneinmancom","machine_tag":0},{"id":"47341397-14090480679-71958970","author":"47434210@N08","authorname":"GeneInman.com","raw":"SnapSeed App.","_content":"snapseedapp","machine_tag":0}]},"urls":{"url":[{"type":"photopage","_content":"https:\/\/www.flickr.com\/photos\/gene_inman\/14090480679\/"}]},"media":"photo"},"stat":"ok"}