{"photo":{"id":"7559856248","secret":"7013dda858","server":"7251","farm":8,"dateuploaded":"1342151794","isfavorite":0,"license":"2","safety_level":"0","rotation":0,"originalsecret":"76b5429f91","originalformat":"jpg","owner":{"nsid":"12155320@N00","username":"Dylan Passmore","realname":"Dylan Passmore","location":"Toronto, Canada","iconserver":"229","iconfarm":1,"path_alias":"dylanpassmore"},"title":{"_content":"10168 (Dylan Passmore)"},"description":{"_content":"Victoria, British Columbia\nCanada\n\n&quot;&quot;\n\n\nBy: Dylan Passmore\n\nKeywords: Auto, Bio-retention area, Bio-swale, Bulb Out, Car, Cars, Catch Basin, Crossing, Curb Extension, Curb Inlet, Drainage, Parking, Parking Lot, Planning, Public Space, Street, Streets, Streetscape, Surface, Transportation"},"visibility":{"ispublic":1,"isfriend":0,"isfamily":0},"dates":{"posted":"1342151794","taken":"2012-06-24 10:24:42","takengranularity":"0","takenunknown":0,"lastupdate":"1383232378"},"views":"834","editability":{"cancomment":0,"canaddmeta":0},"publiceditability":{"cancomment":1,"canaddmeta":0},"usage":{"candownload":1,"canblog":0,"canprint":0,"canshare":1},"comments":{"_content":"0"},"notes":{"note":[]},"people":{"haspeople":0},"tags":{"tag":[{"id":"4159399-7559856248-33","author":"12155320@N00","authorname":"Dylan Passmore","raw":"Auto","_content":"auto","machine_tag":0},{"id":"4159399-7559856248-54673904","author":"12155320@N00","authorname":"Dylan Passmore","raw":"Bio-retention area","_content":"bioretentionarea","machine_tag":0},{"id":"4159399-7559856248-2590362","author":"12155320@N00","authorname":"Dylan Passmore","raw":"Bio-swale","_content":"bioswale","machine_tag":0},{"id":"4159399-7559856248-13201377","author":"12155320@N00","authorname":"Dylan Passmore","raw":"Bulb Out","_content":"bulbout","machine_tag":0},{"id":"4159399-7559856248-923","author":"12155320@N00","authorname":"Dylan Passmore","raw":"Car","_content":"car","machine_tag":0},{"id":"4159399-7559856248-623","author":"12155320@N00","authorname":"Dylan Passmore","raw":"Cars","_content":"cars","machine_tag":0},{"id":"4159399-7559856248-3205620","author":"12155320@N00","authorname":"Dylan Passmore","raw":"Catch Basin","_content":"catchbasin","machine_tag":0},{"id":"4159399-7559856248-3777","author":"12155320@N00","authorname":"Dylan Passmore","raw":"Crossing","_content":"crossing","machine_tag":0},{"id":"4159399-7559856248-5005011","author":"12155320@N00","authorname":"Dylan Passmore","raw":"Curb Extension","_content":"curbextension","machine_tag":0},{"id":"4159399-7559856248-54673942","author":"12155320@N00","authorname":"Dylan Passmore","raw":"Curb Inlet","_content":"curbinlet","machine_tag":0},{"id":"4159399-7559856248-119507","author":"12155320@N00","authorname":"Dylan Passmore","raw":"Drainage","_content":"drainage","machine_tag":0},{"id":"4159399-7559856248-6159","author":"12155320@N00","authorname":"Dylan Passmore","raw":"Parking","_content":"parking","machine_tag":0},{"id":"4159399-7559856248-3017","author":"12155320@N00","authorname":"Dylan Passmore","raw":"Parking Lot","_content":"parkinglot","machine_tag":0},{"id":"4159399-7559856248-13555","author":"12155320@N00","authorname":"Dylan Passmore","raw":"Planning","_content":"planning","machine_tag":0},{"id":"4159399-7559856248-1195","author":"12155320@N00","authorname":"Dylan Passmore","raw":"Public Space","_content":"publicspace","machine_tag":0},{"id":"4159399-7559856248-85","author":"12155320@N00","authorname":"Dylan Passmore","raw":"Street","_content":"street","machine_tag":0},{"id":"4159399-7559856248-505","author":"12155320@N00","authorname":"Dylan Passmore","raw":"Streets","_content":"streets","machine_tag":0},{"id":"4159399-7559856248-48735","author":"12155320@N00","authorname":"Dylan Passmore","raw":"Streetscape","_content":"streetscape","machine_tag":0},{"id":"4159399-7559856248-9523","author":"12155320@N00","authorname":"Dylan Passmore","raw":"Surface","_content":"surface","machine_tag":0},{"id":"4159399-7559856248-14973","author":"12155320@N00","authorname":"Dylan Passmore","raw":"Transportation","_content":"transportation","machine_tag":0},{"id":"4159399-7559856248-9609","author":"12155320@N00","authorname":"Dylan Passmore","raw":"Victoria","_content":"victoria","machine_tag":0},{"id":"4159399-7559856248-5250","author":"12155320@N00","authorname":"Dylan Passmore","raw":"British Columbia","_content":"britishcolumbia","machine_tag":0},{"id":"4159399-7559856248-451","author":"12155320@N00","authorname":"Dylan Passmore","raw":"Canada","_content":"canada","machine_tag":0}]},"urls":{"url":[{"type":"photopage","_content":"https:\/\/www.flickr.com\/photos\/dylanpassmore\/7559856248\/"}]},"media":"photo"},"stat":"ok"}