{"photo":{"person":[{"nsid":"21997775@N07","username":"Italberto Dantas","realname":"Italberto Figueira Dantas","favedate":"1436209274","iconserver":"450","iconfarm":1,"contact":0,"friend":0,"family":0},{"nsid":"52559257@N02","username":"benbobjr","realname":"Ben Abel","favedate":"1435944393","iconserver":"5484","iconfarm":6,"contact":0,"friend":0,"family":0},{"nsid":"100781634@N02","username":"Onurah Art","realname":"Anna Spiakowska","favedate":"1435936147","iconserver":"5481","iconfarm":6,"contact":0,"friend":0,"family":0},{"nsid":"82293232@N03","username":"old Man with Charm","realname":"CardCollector & HobbyPhotographer","favedate":"1435913529","iconserver":"3890","iconfarm":4,"contact":0,"friend":0,"family":0},{"nsid":"132717081@N06","username":"konstantin.tilberg","realname":"Konstantin Tilberg","favedate":"1435911656","iconserver":"3907","iconfarm":4,"contact":0,"friend":0,"family":0},{"nsid":"78683307@N04","username":"~\u5c0f\u4e56~ Y.C.CHEN","realname":"Yu-Cheng Chen","favedate":"1435909511","iconserver":"8871","iconfarm":9,"contact":0,"friend":0,"family":0},{"nsid":"46706608@N06","username":"Syahrel Azha Hashim","realname":"Syahrel Hashim","favedate":"1435881624","iconserver":"332","iconfarm":1,"contact":0,"friend":0,"family":0},{"nsid":"127408554@N06","username":"siam.javanbakht","realname":"Siamak Javanbakht","favedate":"1435876042","iconserver":"7353","iconfarm":8,"contact":0,"friend":0,"family":0}],"id":"18743303583","secret":"9643eb9154","server":"317","farm":1,"page":1,"pages":1,"perpage":10,"total":"8"},"stat":"ok"}